README.txt
setup.py
collective/__init__.py
collective.portlet.references.egg-info/PKG-INFO
collective.portlet.references.egg-info/SOURCES.txt
collective.portlet.references.egg-info/dependency_links.txt
collective.portlet.references.egg-info/entry_points.txt
collective.portlet.references.egg-info/namespace_packages.txt
collective.portlet.references.egg-info/not-zip-safe
collective.portlet.references.egg-info/requires.txt
collective.portlet.references.egg-info/top_level.txt
collective/portlet/__init__.py
collective/portlet/references/TODO.txt
collective/portlet/references/__init__.py
collective/portlet/references/configure.zcml
collective/portlet/references/referencesportlet.pt
collective/portlet/references/referencesportlet.py
collective/portlet/references/version.txt
collective/portlet/references/locales/collective.portlet.references.pot
collective/portlet/references/locales/es/LC_MESSAGES/collective.portlet.references.mo
collective/portlet/references/locales/es/LC_MESSAGES/collective.portlet.references.po
collective/portlet/references/locales/fr/LC_MESSAGES/collective.portlet.references.mo
collective/portlet/references/locales/fr/LC_MESSAGES/collective.portlet.references.po
collective/portlet/references/profiles/default/metadata.xml
collective/portlet/references/profiles/default/portlets.xml
collective/portlet/references/tests/__init__.py
collective/portlet/references/tests/base.py
collective/portlet/references/tests/test_portlet.py
docs/HISTORY.txt
docs/INSTALL.txt
docs/LICENSE.GPL
docs/LICENSE.txt
