Metadata-Version: 1.0
Name: collective.portlet.references
Version: 1.0
Summary: Display references of a page
Home-page: http://pypi.python.org/pypi/collective.portlet.references
Author: Zest Software
Author-email: m.van.rees@zestsoftware.nl
License: GPL
Platform: UNKNOWN
Classifier: Framework :: Plone
Classifier: Programming Language :: Python
Classifier: Topic :: Software Development :: Libraries :: Python Modules
